README.rst
dxr.py
setup.py
dxr_cmd.egg-info/PKG-INFO
dxr_cmd.egg-info/SOURCES.txt
dxr_cmd.egg-info/dependency_links.txt
dxr_cmd.egg-info/entry_points.txt
dxr_cmd.egg-info/requires.txt
dxr_cmd.egg-info/top_level.txt