Metadata-Version: 1.0
Name: dxr-cmd
Version: 0.2.2
Summary: Command-line tool for querying DXR.
Home-page: https://github.com/Osmose/dxr
Author: Michael Kelly
Author-email: me@mkelly.me
License: MIT
Platform: UNKNOWN
